setup.py
abduy_dist.egg-info/PKG-INFO
abduy_dist.egg-info/SOURCES.txt
abduy_dist.egg-info/dependency_links.txt
abduy_dist.egg-info/not-zip-safe
abduy_dist.egg-info/top_level.txt
distributions/Binomialdistribution.py
distributions/Gaussiandistribution.py
distributions/Generaldistribution.py
distributions/__init__.py