Metadata-Version: 1.0
Name: abduy-dist
Version: 0.1
Summary: abduy_dist
Home-page: UNKNOWN
Author: UNKNOWN
Author-email: UNKNOWN
License: UNKNOWN
Platform: UNKNOWN
